cdk_http_pinger/__init__.py
cdk_http_pinger/py.typed
cdk_http_pinger/_jsii/__init__.py
cdk_http_pinger/_jsii/cdk-http-pinger@0.1.222.jsii.tgz
cdk_http_pinger-0.1.222.dist-info/LICENSE
cdk_http_pinger-0.1.222.dist-info/METADATA
cdk_http_pinger-0.1.222.dist-info/WHEEL
cdk_http_pinger-0.1.222.dist-info/top_level.txt
cdk_http_pinger-0.1.222.dist-info/RECORD
